hassette/__init__.py
hassette/__main__.py
hassette/api/__init__.py
hassette/api/api.py
hassette/api/sync.py
hassette/app/__init__.py
hassette/app/app.py
hassette/app/app_config.py
hassette/app/utils.py
hassette/bus/__init__.py
hassette/bus/bus.py
hassette/bus/extraction.py
hassette/bus/injection.py
hassette/bus/listeners.py
hassette/bus/rate_limiter.py
hassette/config/__init__.py
hassette/config/classes.py
hassette/config/config.py
hassette/config/defaults.py
hassette/config/hassette.dev.toml
hassette/config/hassette.prod.toml
hassette/config/helpers.py
hassette/const/__init__.py
hassette/const/colors.py
hassette/const/misc.py
hassette/const/sensor.py
hassette/context.py
hassette/core/__init__.py
hassette/core/api_resource.py
hassette/core/app_handler.py
hassette/core/bus_service.py
hassette/core/core.py
hassette/core/file_watcher.py
hassette/core/health_service.py
hassette/core/scheduler_service.py
hassette/core/service_watcher.py
hassette/core/state_proxy.py
hassette/core/state_registry.py
hassette/core/type_registry.py
hassette/core/websocket_service.py
hassette/event_handling/__init__.py
hassette/event_handling/accessors.py
hassette/event_handling/conditions.py
hassette/event_handling/dependencies.py
hassette/event_handling/predicates.py
hassette/events/__init__.py
hassette/events/base.py
hassette/events/hass/__init__.py
hassette/events/hass/hass.py
hassette/events/hass/raw.py
hassette/events/hassette.py
hassette/exceptions.py
hassette/logging_.py
hassette/models/__init__.py
hassette/models/entities/__init__.py
hassette/models/entities/base.py
hassette/models/entities/light.py
hassette/models/history.py
hassette/models/services.py
hassette/models/states/__init__.py
hassette/models/states/air_quality.py
hassette/models/states/alarm_control_panel.py
hassette/models/states/assist_satellite.py
hassette/models/states/automation.py
hassette/models/states/base.py
hassette/models/states/calendar.py
hassette/models/states/camera.py
hassette/models/states/climate.py
hassette-0.19.2.dist-info/WHEEL
hassette-0.19.2.dist-info/entry_points.txt
hassette-0.19.2.dist-info/METADATA
hassette-0.19.2.dist-info/RECORD
