Metadata-Version: 2.4
Name: hassette
Version: 0.19.2
Summary: Hassette is a simple, modern, async-first Python framework for building Home Assistant automations.
Keywords: home-assistant,automation,async,typed,framework,smart-home,iot
Author: Jessica
Author-email: Jessica <12jessicasmith34@gmail.com>
License-Expression: MIT
Classifier: Development Status :: 4 - Beta
Classifier: Intended Audience :: Developers
Classifier: License :: OSI Approved :: MIT License
Classifier: Programming Language :: Python :: 3
Classifier: Programming Language :: Python :: 3.11
Classifier: Programming Language :: Python :: 3.12
Classifier: Programming Language :: Python :: 3.13
Classifier: Topic :: Home Automation
Classifier: Topic :: Software Development :: Libraries :: Python Modules
Classifier: Framework :: AsyncIO
Classifier: Typing :: Typed
Requires-Dist: aiohttp>=3.11.18
Requires-Dist: anyio>=4.10.0
Requires-Dist: coloredlogs>=15.0.1
Requires-Dist: croniter>=6.0.0
Requires-Dist: deepdiff>=8.6.1
Requires-Dist: diskcache>=5.6.3
Requires-Dist: fair-async-rlock>=1.0.7
Requires-Dist: frozendict>=2.4.7
Requires-Dist: glom>=24.11.0
Requires-Dist: humanize>=4.13.0
Requires-Dist: orjson>=3.10.18
Requires-Dist: packaging>=25.0
Requires-Dist: platformdirs>=4.3.8
Requires-Dist: pydantic-settings>=2.10.0
Requires-Dist: python-dotenv>=1.1.0
Requires-Dist: tenacity>=9.1.2
Requires-Dist: typing-extensions==4.15.*
Requires-Dist: watchfiles>=1.1.0
Requires-Dist: whenever==0.9.*
Requires-Python: >=3.11, <3.14
Project-URL: Homepage, https://github.com/nodejsmith/hassette
Project-URL: Repository, https://github.com/nodejsmith/hassette
Project-URL: Documentation, https://github.com/nodejsmith/hassette#readme
Project-URL: Bug Reports, https://github.com/nodejsmith/hassette/issues
Project-URL: Changelog, https://github.com/nodejsmith/hassette/blob/main/CHANGELOG.md
